Metadata-Version: 2.1
Name: odoo12-addon-analytic-tag-dimension-enhanced
Version: 12.0.2.0.0
Summary: Analytic Accounts Dimensions Enhanced
Home-page: https://github.com/OCA/account-analytic
Author: Ecosoft, Odoo Community Association (OCA)
Author-email: support@odoo-community.org
License: AGPL-3
Platform: UNKNOWN
Classifier: Programming Language :: Python
Classifier: Framework :: Odoo
Classifier: License :: OSI Approved :: GNU Affero General Public License v3
Requires-Python: >=3.5
Requires-Dist: odoo12-addon-analytic-tag-dimension
Requires-Dist: odoo (<12.1dev,>=12.0a)
